README
setup.py
msgpack_pure/__init__.py
msgpack_pure/__version__.py
msgpack_pure/_core.py
msgpack_pure.egg-info/PKG-INFO
msgpack_pure.egg-info/SOURCES.txt
msgpack_pure.egg-info/dependency_links.txt
msgpack_pure.egg-info/top_level.txt