Metadata-Version: 1.0
Name: msgpack-pure
Version: 0.1.3
Summary: MessagePack (de)serializer written in pure Python.
Home-page: http://msgpack.org/
Author: Keisuke Fukuda
Author-email: keisukefukuda@gmail.com
License: Apache License 2
Download-URL: http://pypi.python.org/pypi/msgpack-pure/
Platform: UNKNOWN
Classifier: Programming Language :: Python :: 2
Classifier: Development Status :: 3 - Alpha
Classifier: Intended Audience :: Developers
Classifier: License :: OSI Approved :: Apache Software License
